computer-architechture/Distribution/HDL_CODE/Adder1bit.v
module Adder1bit (
    input  A,
    input  B,
    input  Cin,
    output S,
    output Cout
);
  assign S = A ^ B ^ Cin;
  assign Cout = (A & B) | (A ^ B) & Cin;
endmodule

computer-architechture/Distribution/HDL_CODE/Adder1bit_tb.v
`timescale 1ns / 1ps

module Adder1bit_tb ();
  reg  A;
  reg  B;
  reg  Cin;
  wire S;
  wire Cout;

  Adder1bit uut (
      .A(A),
      .B(B),
      .Cin(Cin),
      .S(S),
      .Cout(Cout)
  );
  initial begin
    $dumpfile("test.vcd");
    $dumpvars(0, Adder1bit_tb);

    Cin = 1'b0;
    A   = 1'b0;
    B   = 1'b0;

    #20;
    Cin = 1'b0;
    A   = 1'b0;
    B   = 1'b1;

    #20;
    Cin = 1'b0;
    A   = 1'b1;
    B   = 1'b0;

    #20;
    Cin = 1'b0;
    A   = 1'b1;
    B   = 1'b1;

    #20;
    Cin = 1'b1;
    A   = 1'b0;
    B   = 1'b0;

    #20;
    Cin = 1'b1;
    A   = 1'b0;
    B   = 1'b1;

    #20;
    Cin = 1'b1;
    A   = 1'b1;
    B   = 1'b0;

    #20;
    Cin = 1'b1;
    A   = 1'b1;
    B   = 1'b1;

    $finish;
  end

  initial begin
    $monitor("Cin = %b, A = %b, B=%b, Cout =%b, S =%b\n", Cin, A, B, Cout, S);
  end
endmodule

computer-architechture/Distribution/HDL_CODE/test.vcd
$date
	Tue Apr 15 15:31:25 2025
$end
$version
	Icarus Verilog
$end
$timescale
	1ps
$end
$scope module Adder1bit_tb $end
$var wire 1 ! S $end
$var wire 1 " Cout $end
$var reg 1 # A $end
$var reg 1 $ B $end
$var reg 1 % Cin $end
$scope module uut $end
$var wire 1 # A $end
$var wire 1 $ B $end
$var wire 1 % Cin $end
$var wire 1 " Cout $end
$var wire 1 ! S $end
$upscope $end
$upscope $end
$enddefinitions $end
$comment Show the parameter values. $end
$dumpall
$end
#0
$dumpvars
0%
0$
0#
0"
0!
$end
#20000
1!
1$
#40000
0$
1#
#60000
0!
1"
1$
#80000
0"
1!
0$
0#
1%
#100000
1"
0!
1$
#120000
0$
1#
#140000
1!
1$
