computer-architechture/Distribution/HDL_CODE/Subtractor1bit.v
module Subtractor1bit (
    input A,
    input B,
    input Bin,
    output D,
    output Bout
);
assign D = A ^ B ^ Bin;
assign Bout = (B & Bin) | (!A & B) | (!A & Bin); 
endmodule

computer-architechture/Distribution/HDL_CODE/Subtractor1bit_tb.v
`timescale 1ns/1ps

module Subtractor1bit_tb();
    reg A;
    reg B;
    reg Bin;
    wire D;
    wire Bout;

    Subtractor1bit uut(A, B, Bin, D, Bout);
    initial begin
        $dumpfile("test_sub1bit.vcd");
        $dumpvars(0, Subtractor1bit_tb);

        Bin = 1'b0;
        A = 1'b0;
        B = 1'b0;

        #20;
        Bin = 1'b0;
        A = 1'b0;
        B = 1'b1;

        #20;
        Bin = 1'b0;
        A = 1'b1;
        B = 1'b0;

        #20;
        Bin = 1'b0;
        A = 1'b1;
        B = 1'b1;

        #20;
        Bin = 1'b1;
        A = 1'b0;
        B = 1'b0;

        #20;
        Bin = 1'b1;
        A = 1'b0;
        B = 1'b1;

        #20;
        Bin = 1'b1;
        A = 1'b1;
        B = 1'b0;

        #20;
        Bin = 1'b1;
        A = 1'b1;
        B = 1'b1;

        $finish;
    end

    initial begin
        $monitor("A = %b, B=%b, Bin = %b, D =%b, Bout =%b\n",A, B, Bin, D, Bout);
    end
endmodule

computer-architechture/Distribution/HDL_CODE/test_sub1bit.vcd
$date
	Tue Apr 15 15:54:00 2025
$end
$version
	Icarus Verilog
$end
$timescale
	1ps
$end
$scope module Subtractor1bit_tb $end
$var wire 1 ! D $end
$var wire 1 " Bout $end
$var reg 1 # A $end
$var reg 1 $ B $end
$var reg 1 % Bin $end
$scope module uut $end
$var wire 1 # A $end
$var wire 1 $ B $end
$var wire 1 % Bin $end
$var wire 1 " Bout $end
$var wire 1 ! D $end
$upscope $end
$upscope $end
$enddefinitions $end
$comment Show the parameter values. $end
$dumpall
$end
#0
$dumpvars
0%
0$
0#
0"
0!
$end
#20000
1"
1!
1$
#40000
0"
0$
1#
#60000
0!
1$
#80000
1"
1!
0$
0#
1%
#100000
0!
1$
#120000
0"
0$
1#
#140000
1"
1!
1$
